{
  "@type": "NewsArticle",
  "identifier": "2022--02--13--en--showhn--HackerNews--NewsArticle--30321333",
  "url": "https://news.ycombinator.com/item?id=30321333",
  "headline": "Show HN: Wicked Invaders: A 1980s-arcade-style game using HTML5 Canvas/Web Audio",
  "publisher": {
    "@type": "Organization",
    "name": "HackerNews",
    "url": "https://news.ycombinator.com",
    "logo": "https://hn.buzzing.cc/avatar.png"
  },
  "description": "",
  "keywords": [
    "Show HN"
  ],
  "genre": "Show HN",
  "author": {
    "@type": "Person",
    "name": "susam",
    "url": "https://news.ycombinator.com/user?id=susam"
  },
  "discussionUrl": "https://news.ycombinator.com/item?id=30321333",
  "sameAs": "https://susam.net/invaders.html",
  "dateCreated": "2022-02-13T12:40:37.255Z",
  "datePublished": "2022-02-13T12:39:37.000Z",
  "dateModified": "2022-02-13T12:40:37.255Z",
  "interactionStatistic": [
    {
      "@type": "InteractionCounter",
      "interactionType": {
        "@type": "LikeAction"
      },
      "userInteractionCount": 1
    },
    {
      "@type": "InteractionCounter",
      "interactionType": {
        "@type": "CommentAction"
      },
      "userInteractionCount": 0
    }
  ],
  "headline_zh-Hans": "Show HN: 邪恶的入侵者。使用HTML5画布/网络音频的80年代街机风格游戏",
  "headline_zh-Hant": "Show HN: 邪惡的入侵者。使用HTML5畫布/網絡音頻的80年代街機風格遊戲",
  "@context": [
    "https://schema.org",
    {
      "@vocab": "http://schema.org/",
      "@language": "en",
      "headline_zh-Hans": {
        "@id": "headline",
        "@language": "zh-Hans"
      },
      "headline_zh-Hant": {
        "@id": "headline",
        "@language": "zh-Hant"
      },
      "@version": 1.1
    }
  ]
}