{
  "@type": "NewsArticle",
  "identifier": "2022--02--08--en--showhn--HackerNews--NewsArticle--30256865",
  "url": "https://news.ycombinator.com/item?id=30256865",
  "headline": "Show HN: Phront – Discover and apply to the best schools in your area",
  "publisher": {
    "@type": "Organization",
    "name": "HackerNews",
    "url": "https://news.ycombinator.com",
    "logo": "https://hn.buzzing.cc/avatar.png"
  },
  "description": "",
  "keywords": [
    "Show HN"
  ],
  "genre": "Show HN",
  "author": {
    "@type": "Person",
    "name": "michaeltendo",
    "url": "https://news.ycombinator.com/user?id=michaeltendo"
  },
  "discussionUrl": "https://news.ycombinator.com/item?id=30256865",
  "sameAs": "https://phront.page/",
  "dateCreated": "2022-02-08T10:39:51.307Z",
  "datePublished": "2022-02-08T10:34:47.000Z",
  "dateModified": "2022-02-08T10:39:51.307Z",
  "interactionStatistic": [
    {
      "@type": "InteractionCounter",
      "interactionType": {
        "@type": "LikeAction"
      },
      "userInteractionCount": 1
    },
    {
      "@type": "InteractionCounter",
      "interactionType": {
        "@type": "CommentAction"
      },
      "userInteractionCount": 0
    }
  ],
  "headline_zh-Hans": "Show HN: Phront - 发现并申请您所在地区的最佳学校",
  "headline_zh-Hant": "Show HN: Phront - 發現並申請您所在地區的最佳學校",
  "@context": [
    "https://schema.org",
    {
      "@vocab": "http://schema.org/",
      "@language": "en",
      "headline_zh-Hans": {
        "@id": "headline",
        "@language": "zh-Hans"
      },
      "headline_zh-Hant": {
        "@id": "headline",
        "@language": "zh-Hant"
      },
      "@version": 1.1
    }
  ]
}