{
  "@type": "NewsArticle",
  "identifier": "2022--03--10--en--myrss--derek-thompson--NewsArticle--d931b5ef6727a4be76879a47db9245c8",
  "url": "https://www.theatlantic.com/newsletters/archive/2022/03/russia-economic-sanctions-wheat-oil/627004/?utm_source=feed",
  "headline": "Russia’s Economic Blackout Will Change the World",
  "publisher": {
    "@type": "Organization",
    "name": "www.theatlantic.com",
    "url": "https://www.theatlantic.com/feed/all/"
  },
  "description": "Like all novel experiments, the group punishment of Russia is a leap into the unknown.",
  "keywords": [],
  "author": {
    "@type": "Person",
    "name": "Derek Thompson",
    "url": "https://www.theatlantic.com/feed/all/"
  },
  "discussionUrl": "https://www.theatlantic.com/newsletters/archive/2022/03/russia-economic-sanctions-wheat-oil/627004/?utm_source=feed",
  "sameAs": "https://www.theatlantic.com/newsletters/archive/2022/03/russia-economic-sanctions-wheat-oil/627004/?utm_source=feed",
  "dateCreated": "2022-03-10T17:44:30.223Z",
  "datePublished": "2022-03-10T16:56:53.000Z",
  "dateModified": "2022-03-10T17:44:30.223Z",
  "interactionStatistic": []
}