{
  "@type": "NewsArticle",
  "identifier": "2022--02--04--en--askhn--HackerNews--NewsArticle--30209117",
  "url": "https://news.ycombinator.com/item?id=30209117",
  "headline": "If Meta dies will React follow",
  "publisher": {
    "@type": "Organization",
    "name": "HackerNews",
    "url": "https://news.ycombinator.com",
    "logo": "https://hn.buzzing.cc/avatar.png"
  },
  "description": "",
  "keywords": [
    "Ask HN"
  ],
  "genre": "Ask HN",
  "author": {
    "@type": "Person",
    "name": "friendlydog",
    "url": "https://news.ycombinator.com/user?id=friendlydog"
  },
  "discussionUrl": "https://news.ycombinator.com/item?id=30209117",
  "sameAs": "https://news.ycombinator.com/item?id=30209117",
  "dateCreated": "2022-02-04T17:10:54.463Z",
  "datePublished": "2022-02-04T16:41:39.000Z",
  "dateModified": "2022-02-04T17:10:54.463Z",
  "interactionStatistic": [
    {
      "@type": "InteractionCounter",
      "interactionType": {
        "@type": "LikeAction"
      },
      "userInteractionCount": 8
    },
    {
      "@type": "InteractionCounter",
      "interactionType": {
        "@type": "CommentAction"
      },
      "userInteractionCount": 9
    }
  ]
}