{
  "@type": "NewsArticle",
  "identifier": "2022--03--20--en--myrss--erin-overbey--NewsArticle--b5f5f0343ae4854c66bb1a5c3da8ecef",
  "url": "https://www.newyorker.com/books/double-take/sunday-reading-luminaries-of-the-theatre",
  "headline": "Sunday Reading: Luminaries of the Theatre",
  "publisher": {
    "@type": "Organization",
    "name": "www.newyorker.com",
    "url": "https://www.newyorker.com/feed/culture"
  },
  "description": "From the magazine’s archive: a selection of pieces about the theatrical experience.",
  "keywords": [],
  "author": {
    "@type": "Person",
    "name": "Erin Overbey",
    "url": "https://www.newyorker.com/feed/culture"
  },
  "discussionUrl": "https://www.newyorker.com/books/double-take/sunday-reading-luminaries-of-the-theatre",
  "sameAs": "https://www.newyorker.com/books/double-take/sunday-reading-luminaries-of-the-theatre",
  "dateCreated": "2022-03-20T10:10:46.859Z",
  "datePublished": "2022-03-20T10:00:00.000Z",
  "dateModified": "2022-03-20T10:10:46.859Z",
  "interactionStatistic": [],
  "headline_zh-Hans": "主日阅读。戏剧的光辉人物",
  "headline_zh-Hant": "主日閱讀。戲劇的光輝人物",
  "@context": [
    "https://schema.org",
    {
      "@vocab": "http://schema.org/",
      "@language": "en",
      "headline_zh-Hans": {
        "@id": "headline",
        "@language": "zh-Hans"
      },
      "headline_zh-Hant": {
        "@id": "headline",
        "@language": "zh-Hant"
      },
      "@version": 1.1,
      "description_zh-Hans": {
        "@id": "description",
        "@language": "zh-Hans"
      },
      "description_zh-Hant": {
        "@id": "description",
        "@language": "zh-Hant"
      }
    }
  ],
  "description_zh-Hans": "来自该杂志的档案：关于戏剧经验的精选文章。",
  "description_zh-Hant": "來自該雜誌的檔案：關於戲劇經驗的精選文章。"
}