{
  "@type": "NewsArticle",
  "identifier": "2022--04--13--en--hackernews--HackerNews--NewsArticle--31013994",
  "url": "https://news.ycombinator.com/item?id=31013994",
  "headline": "Dutch scandal serves as a warning for Europe over risks of using algorithms",
  "publisher": {
    "@type": "Organization",
    "name": "HackerNews",
    "url": "https://news.ycombinator.com",
    "logo": "https://hn.buzzing.cc/avatar.png"
  },
  "description": "",
  "keywords": [],
  "author": {
    "@type": "Person",
    "name": "Kiala",
    "url": "https://news.ycombinator.com/user?id=Kiala"
  },
  "discussionUrl": "https://news.ycombinator.com/item?id=31013994",
  "sameAs": "https://www.politico.eu/article/dutch-scandal-serves-as-a-warning-for-europe-over-risks-of-using-algorithms/",
  "dateCreated": "2022-04-13T13:23:24.332Z",
  "datePublished": "2022-04-13T12:49:56.000Z",
  "dateModified": "2022-04-13T13:23:24.332Z",
  "interactionStatistic": [
    {
      "@type": "InteractionCounter",
      "interactionType": {
        "@type": "LikeAction"
      },
      "userInteractionCount": 27
    },
    {
      "@type": "InteractionCounter",
      "interactionType": {
        "@type": "CommentAction"
      },
      "userInteractionCount": 11
    }
  ],
  "headline_zh-Hans": "荷兰的丑闻是对欧洲使用算法的风险的警告",
  "headline_zh-Hant": "荷蘭的醜聞是對歐洲使用算法的風險的警告",
  "@context": [
    "https://schema.org",
    {
      "@vocab": "http://schema.org/",
      "@language": "en",
      "headline_zh-Hans": {
        "@id": "headline",
        "@language": "zh-Hans"
      },
      "headline_zh-Hant": {
        "@id": "headline",
        "@language": "zh-Hant"
      },
      "@version": 1.1
    }
  ]
}