{
  "@type": "NewsArticle",
  "identifier": "2022--06--30--en--hackernews--HackerNews--NewsArticle--31932779",
  "url": "https://news.ycombinator.com/item?id=31932779",
  "headline": "Seattle software firm Outreach.io employee fired for not liking bodegas",
  "publisher": {
    "@type": "Organization",
    "name": "HackerNews",
    "url": "https://news.ycombinator.com",
    "logo": "https://hn.buzzing.cc/avatar.png"
  },
  "description": "",
  "keywords": [],
  "author": {
    "@type": "Person",
    "name": "sergiotapia",
    "url": "https://news.ycombinator.com/user?id=sergiotapia"
  },
  "discussionUrl": "https://news.ycombinator.com/item?id=31932779",
  "sameAs": "https://twitter.com/scuffedbob/status/1542285785906286594",
  "dateCreated": "2022-06-30T14:56:37.306Z",
  "datePublished": "2022-06-30T14:30:02.000Z",
  "dateModified": "2022-06-30T14:56:37.306Z",
  "interactionStatistic": [
    {
      "@type": "InteractionCounter",
      "interactionType": {
        "@type": "LikeAction"
      },
      "userInteractionCount": 14
    },
    {
      "@type": "InteractionCounter",
      "interactionType": {
        "@type": "CommentAction"
      },
      "userInteractionCount": 5
    }
  ],
  "headline_zh-Hans": "西雅图软件公司Outreach.io员工因不喜欢酒馆被解雇\n",
  "headline_zh-Hant": "西雅圖軟件公司Outreach.io員工因不喜歡酒館被解僱\n",
  "@context": [
    "https://schema.org",
    {
      "@vocab": "http://schema.org/",
      "@language": "en",
      "headline_zh-Hans": {
        "@id": "headline",
        "@language": "zh-Hans"
      },
      "headline_zh-Hant": {
        "@id": "headline",
        "@language": "zh-Hant"
      },
      "@version": 1.1
    }
  ]
}