{
  "@type": "NewsArticle",
  "identifier": "2022--06--28--en--hackernews--HackerNews--NewsArticle--31907151",
  "url": "https://news.ycombinator.com/item?id=31907151",
  "headline": "Council of Europe anti-torture Committee visits the Netherlands",
  "publisher": {
    "@type": "Organization",
    "name": "HackerNews",
    "url": "https://news.ycombinator.com",
    "logo": "https://hn.buzzing.cc/avatar.png"
  },
  "description": "",
  "keywords": [],
  "author": {
    "@type": "Person",
    "name": "Tomte",
    "url": "https://news.ycombinator.com/user?id=Tomte"
  },
  "discussionUrl": "https://news.ycombinator.com/item?id=31907151",
  "sameAs": "https://www.coe.int/en/web/cpt/-/council-of-europe-anti-torture-committee-carries-out-16-day-visit-to-the-netherlands",
  "dateCreated": "2022-06-28T13:46:29.790Z",
  "datePublished": "2022-06-28T13:04:10.000Z",
  "dateModified": "2022-06-28T13:46:29.790Z",
  "interactionStatistic": [
    {
      "@type": "InteractionCounter",
      "interactionType": {
        "@type": "LikeAction"
      },
      "userInteractionCount": 5
    },
    {
      "@type": "InteractionCounter",
      "interactionType": {
        "@type": "CommentAction"
      },
      "userInteractionCount": 0
    }
  ],
  "headline_zh-Hans": "欧洲委员会反酷刑委员会访问荷兰\n",
  "headline_zh-Hant": "歐洲委員會反酷刑委員會訪問荷蘭\n",
  "@context": [
    "https://schema.org",
    {
      "@vocab": "http://schema.org/",
      "@language": "en",
      "headline_zh-Hans": {
        "@id": "headline",
        "@language": "zh-Hans"
      },
      "headline_zh-Hant": {
        "@id": "headline",
        "@language": "zh-Hant"
      },
      "@version": 1.1
    }
  ]
}