{
  "@type": "NewsArticle",
  "identifier": "2022--04--26--en--hackernews--HackerNews--NewsArticle--31153963",
  "url": "https://news.ycombinator.com/item?id=31153963",
  "headline": "I sold 640 copies of my book in one year",
  "publisher": {
    "@type": "Organization",
    "name": "HackerNews",
    "url": "https://news.ycombinator.com",
    "logo": "https://hn.buzzing.cc/avatar.png"
  },
  "description": "",
  "keywords": [],
  "author": {
    "@type": "Person",
    "name": "strzibny",
    "url": "https://news.ycombinator.com/user?id=strzibny"
  },
  "discussionUrl": "https://news.ycombinator.com/item?id=31153963",
  "sameAs": "https://nts.strzibny.name/one-year-of-sales/",
  "dateCreated": "2022-04-26T05:14:59.170Z",
  "datePublished": "2022-04-25T13:07:59.000Z",
  "dateModified": "2022-04-26T05:14:59.170Z",
  "interactionStatistic": [
    {
      "@type": "InteractionCounter",
      "interactionType": {
        "@type": "LikeAction"
      },
      "userInteractionCount": 8
    },
    {
      "@type": "InteractionCounter",
      "interactionType": {
        "@type": "CommentAction"
      },
      "userInteractionCount": 1
    }
  ],
  "headline_zh-Hans": "我在一年内卖出了640本我的书",
  "headline_zh-Hant": "我在一年內賣出了640本我的書",
  "@context": [
    "https://schema.org",
    {
      "@vocab": "http://schema.org/",
      "@language": "en",
      "headline_zh-Hans": {
        "@id": "headline",
        "@language": "zh-Hans"
      },
      "headline_zh-Hant": {
        "@id": "headline",
        "@language": "zh-Hant"
      },
      "@version": 1.1
    }
  ]
}