{
  "@type": "NewsArticle",
  "identifier": "2022--08--04--en--hackernews--HackerNews--NewsArticle--32343610",
  "url": "https://news.ycombinator.com/item?id=32343610",
  "headline": "OmniEdge – an Open source P2P layer 2 VPN infrastructure based on n2n protocol",
  "publisher": {
    "@type": "Organization",
    "name": "HackerNews",
    "url": "https://news.ycombinator.com",
    "logo": "https://hn.buzzing.cc/avatar.png"
  },
  "description": "",
  "keywords": [],
  "author": {
    "@type": "Person",
    "name": "fariszr",
    "url": "https://news.ycombinator.com/user?id=fariszr"
  },
  "discussionUrl": "https://news.ycombinator.com/item?id=32343610",
  "sameAs": "https://omniedge.io/",
  "dateCreated": "2022-08-04T15:31:11.552Z",
  "datePublished": "2022-08-04T14:47:33.000Z",
  "dateModified": "2022-08-04T15:31:11.552Z",
  "interactionStatistic": [
    {
      "@type": "InteractionCounter",
      "interactionType": {
        "@type": "LikeAction"
      },
      "userInteractionCount": 4
    },
    {
      "@type": "InteractionCounter",
      "interactionType": {
        "@type": "CommentAction"
      },
      "userInteractionCount": 1
    }
  ],
  "headline_zh-Hans": "OmniEdge - 一个基于n2n协议的开源P2P第二层VPN基础设施\n",
  "headline_zh-Hant": "OmniEdge - 一個基於n2n協議的開源P2P第二層VPN基礎設施\n",
  "@context": [
    "https://schema.org",
    {
      "@vocab": "http://schema.org/",
      "@language": "en",
      "headline_zh-Hans": {
        "@id": "headline",
        "@language": "zh-Hans"
      },
      "headline_zh-Hant": {
        "@id": "headline",
        "@language": "zh-Hant"
      },
      "@version": 1.1
    }
  ]
}