{
  "@type": "NewsArticle",
  "identifier": "2022--05--01--en--myfeed--HackerNews--NewsArticle--31229143",
  "url": "https://news.ycombinator.com/item?id=31229143",
  "headline": "The Atheist Experience Weekly Callin Show",
  "publisher": {
    "@type": "Organization",
    "name": "HackerNews",
    "url": "https://news.ycombinator.com",
    "logo": "https://hn.buzzing.cc/avatar.png"
  },
  "description": "",
  "keywords": [],
  "author": {
    "@type": "Person",
    "name": "tomrod",
    "url": "https://news.ycombinator.com/user?id=tomrod"
  },
  "discussionUrl": "https://news.ycombinator.com/item?id=31229143",
  "sameAs": "https://www.youtube.com/watch?v=8qgqPqMv4rc",
  "dateCreated": "2022-05-01T23:31:17.019Z",
  "datePublished": "2022-05-01T22:02:25.000Z",
  "dateModified": "2022-05-01T23:31:17.019Z",
  "interactionStatistic": [
    {
      "@type": "InteractionCounter",
      "interactionType": {
        "@type": "LikeAction"
      },
      "userInteractionCount": 2
    },
    {
      "@type": "InteractionCounter",
      "interactionType": {
        "@type": "CommentAction"
      },
      "userInteractionCount": 0
    }
  ]
}