{
  "@type": "NewsArticle",
  "identifier": "2022--02--22--en--myfeed--HackerNews--NewsArticle--30427435",
  "url": "https://news.ycombinator.com/item?id=30427435",
  "headline": "TSMC 3nm Yield Problems May Derail AMD's CPU Plans",
  "publisher": {
    "@type": "Organization",
    "name": "HackerNews",
    "url": "https://news.ycombinator.com",
    "logo": "https://hn.buzzing.cc/avatar.png"
  },
  "description": "",
  "keywords": [],
  "author": {
    "@type": "Person",
    "name": "rbanffy",
    "url": "https://news.ycombinator.com/user?id=rbanffy"
  },
  "discussionUrl": "https://news.ycombinator.com/item?id=30427435",
  "sameAs": "https://www.tomshardware.com/news/tsmc-3nm-yield-problems-may-derail-amds-cpu-plans",
  "dateCreated": "2022-02-22T13:15:55.722Z",
  "datePublished": "2022-02-22T13:07:45.000Z",
  "dateModified": "2022-02-22T13:15:55.722Z",
  "interactionStatistic": [
    {
      "@type": "InteractionCounter",
      "interactionType": {
        "@type": "LikeAction"
      },
      "userInteractionCount": 1
    },
    {
      "@type": "InteractionCounter",
      "interactionType": {
        "@type": "CommentAction"
      },
      "userInteractionCount": 0
    }
  ],
  "headline_zh-Hans": "台积电3纳米产量问题可能使AMD的CPU计划受阻",
  "headline_zh-Hant": "臺積電3納米產量問題可能使AMD的CPU計劃受阻",
  "@context": [
    "https://schema.org",
    {
      "@vocab": "http://schema.org/",
      "@language": "en",
      "headline_zh-Hans": {
        "@id": "headline",
        "@language": "zh-Hans"
      },
      "headline_zh-Hant": {
        "@id": "headline",
        "@language": "zh-Hant"
      },
      "@version": 1.1
    }
  ]
}