{
  "@type": "NewsArticle",
  "identifier": "2022--03--08--en--myfeed--HackerNews--NewsArticle--30598433",
  "url": "https://news.ycombinator.com/item?id=30598433",
  "headline": "Foto-Webcam – High quality online cams",
  "publisher": {
    "@type": "Organization",
    "name": "HackerNews",
    "url": "https://news.ycombinator.com",
    "logo": "https://hn.buzzing.cc/avatar.png"
  },
  "description": "",
  "keywords": [],
  "author": {
    "@type": "Person",
    "name": "andrewryan",
    "url": "https://news.ycombinator.com/user?id=andrewryan"
  },
  "discussionUrl": "https://news.ycombinator.com/item?id=30598433",
  "sameAs": "https://www.foto-webcam.eu/",
  "dateCreated": "2022-03-08T10:32:41.937Z",
  "datePublished": "2022-03-08T10:28:59.000Z",
  "dateModified": "2022-03-08T10:32:41.937Z",
  "interactionStatistic": [
    {
      "@type": "InteractionCounter",
      "interactionType": {
        "@type": "LikeAction"
      },
      "userInteractionCount": 1
    },
    {
      "@type": "InteractionCounter",
      "interactionType": {
        "@type": "CommentAction"
      },
      "userInteractionCount": 0
    }
  ],
  "headline_zh-Hans": "Foto-Webcam - 高质量的在线摄像头",
  "headline_zh-Hant": "Foto-Webcam - 高質量的在線攝像頭",
  "@context": [
    "https://schema.org",
    {
      "@vocab": "http://schema.org/",
      "@language": "en",
      "headline_zh-Hans": {
        "@id": "headline",
        "@language": "zh-Hans"
      },
      "headline_zh-Hant": {
        "@id": "headline",
        "@language": "zh-Hant"
      },
      "@version": 1.1
    }
  ]
}