{
  "@type": "NewsArticle",
  "identifier": "2022--03--02--en--myfeed--HackerNews--NewsArticle--30524980",
  "url": "https://news.ycombinator.com/item?id=30524980",
  "headline": "Search is broken in Windows 11 Notepad",
  "publisher": {
    "@type": "Organization",
    "name": "HackerNews",
    "url": "https://news.ycombinator.com",
    "logo": "https://hn.buzzing.cc/avatar.png"
  },
  "description": "",
  "keywords": [],
  "author": {
    "@type": "Person",
    "name": "gattilorenz",
    "url": "https://news.ycombinator.com/user?id=gattilorenz"
  },
  "discussionUrl": "https://news.ycombinator.com/item?id=30524980",
  "sameAs": "https://virtuallyfun.com/wordpress/2022/02/25/so-i-have-a-splitting-headache/",
  "dateCreated": "2022-03-02T08:12:42.041Z",
  "datePublished": "2022-03-02T08:05:30.000Z",
  "dateModified": "2022-03-02T08:12:42.041Z",
  "interactionStatistic": [
    {
      "@type": "InteractionCounter",
      "interactionType": {
        "@type": "LikeAction"
      },
      "userInteractionCount": 1
    },
    {
      "@type": "InteractionCounter",
      "interactionType": {
        "@type": "CommentAction"
      },
      "userInteractionCount": 0
    }
  ],
  "headline_zh-Hans": "在Windows 11记事本中，搜索被破坏",
  "headline_zh-Hant": "在Windows 11記事本中，搜索被破壞",
  "@context": [
    "https://schema.org",
    {
      "@vocab": "http://schema.org/",
      "@language": "en",
      "headline_zh-Hans": {
        "@id": "headline",
        "@language": "zh-Hans"
      },
      "headline_zh-Hant": {
        "@id": "headline",
        "@language": "zh-Hant"
      },
      "@version": 1.1
    }
  ]
}