{
  "@type": "NewsArticle",
  "identifier": "2022--02--21--en--myfeed--HackerNews--NewsArticle--30415703",
  "url": "https://news.ycombinator.com/item?id=30415703",
  "headline": "California Will Stick Solar Panels over Canals to Fight Two Disasters at Once",
  "publisher": {
    "@type": "Organization",
    "name": "HackerNews",
    "url": "https://news.ycombinator.com",
    "logo": "https://hn.buzzing.cc/avatar.png"
  },
  "description": "",
  "keywords": [],
  "author": {
    "@type": "Person",
    "name": "rbanffy",
    "url": "https://news.ycombinator.com/user?id=rbanffy"
  },
  "discussionUrl": "https://news.ycombinator.com/item?id=30415703",
  "sameAs": "https://gizmodo.com/california-will-stick-solar-panels-over-canals-to-fight-1848550514",
  "dateCreated": "2022-02-21T13:39:38.559Z",
  "datePublished": "2022-02-21T13:36:21.000Z",
  "dateModified": "2022-02-21T13:39:38.559Z",
  "interactionStatistic": [
    {
      "@type": "InteractionCounter",
      "interactionType": {
        "@type": "LikeAction"
      },
      "userInteractionCount": 1
    },
    {
      "@type": "InteractionCounter",
      "interactionType": {
        "@type": "CommentAction"
      },
      "userInteractionCount": 0
    }
  ],
  "headline_zh-Hans": "加利福尼亚州将在运河上安装太阳能电池板，以同时对抗两种灾害",
  "headline_zh-Hant": "加利福尼亞州將在運河上安裝太陽能電池板，以同時對抗兩種災害",
  "@context": [
    "https://schema.org",
    {
      "@vocab": "http://schema.org/",
      "@language": "en",
      "headline_zh-Hans": {
        "@id": "headline",
        "@language": "zh-Hans"
      },
      "headline_zh-Hant": {
        "@id": "headline",
        "@language": "zh-Hant"
      },
      "@version": 1.1
    }
  ]
}