{
  "@type": "NewsArticle",
  "identifier": "2022--06--29--en--myfeed--HackerNews--NewsArticle--31918763",
  "url": "https://news.ycombinator.com/item?id=31918763",
  "headline": "2022 Bet Awards: Summer Walker’s Outfit in Controversy",
  "publisher": {
    "@type": "Organization",
    "name": "HackerNews",
    "url": "https://news.ycombinator.com",
    "logo": "https://hn.buzzing.cc/avatar.png"
  },
  "description": "",
  "keywords": [],
  "author": {
    "@type": "Person",
    "name": "bulletinbuzz",
    "url": "https://news.ycombinator.com/user?id=bulletinbuzz"
  },
  "discussionUrl": "https://news.ycombinator.com/item?id=31918763",
  "sameAs": "https://viralnewly.com/entertainment/2022-bet-awards-summer-walkers-outfit-in-controversy/",
  "dateCreated": "2022-06-29T11:42:39.430Z",
  "datePublished": "2022-06-29T11:34:01.000Z",
  "dateModified": "2022-06-29T11:42:39.430Z",
  "interactionStatistic": [
    {
      "@type": "InteractionCounter",
      "interactionType": {
        "@type": "LikeAction"
      },
      "userInteractionCount": 2
    },
    {
      "@type": "InteractionCounter",
      "interactionType": {
        "@type": "CommentAction"
      },
      "userInteractionCount": 0
    }
  ],
  "headline_zh-Hans": "2022年博彩奖。夏日行者的装束引起争论\n",
  "headline_zh-Hant": "2022年博彩獎。夏日行者的裝束引起爭論\n",
  "@context": [
    "https://schema.org",
    {
      "@vocab": "http://schema.org/",
      "@language": "en",
      "headline_zh-Hans": {
        "@id": "headline",
        "@language": "zh-Hans"
      },
      "headline_zh-Hant": {
        "@id": "headline",
        "@language": "zh-Hant"
      },
      "@version": 1.1
    }
  ]
}