{
  "@type": "NewsArticle",
  "identifier": "2022--08--08--en--myfeed--lawrence-ulrich--NewsArticle--36e3f255ea21bee443e8e3f09095a815",
  "url": "https://www.nytimes.com/2022/08/05/business/plug-in-hybrid-electric-cars.html",
  "headline": "Plug-In Hybrid Cars Gain Ground in Race With Electric Rivals",
  "publisher": {
    "@type": "Organization",
    "name": "rss.nytimes.com",
    "url": "https://rss.nytimes.com/services/xml/rss/nyt/Technology.xml"
  },
  "description": "There has been a surge in the sales of cars that can travel short distances on just electricity and have a gasoline engine for longer trips.",
  "keywords": [],
  "author": {
    "@type": "Person",
    "name": "Lawrence Ulrich",
    "url": "https://rss.nytimes.com/services/xml/rss/nyt/Technology.xml"
  },
  "discussionUrl": "https://www.nytimes.com/2022/08/05/business/plug-in-hybrid-electric-cars.html",
  "sameAs": "https://www.nytimes.com/2022/08/05/business/plug-in-hybrid-electric-cars.html",
  "dateCreated": "2022-08-08T14:27:21.182Z",
  "datePublished": "2022-08-05T09:00:25.000Z",
  "dateModified": "2022-08-08T14:27:21.182Z",
  "interactionStatistic": [],
  "headline_zh-Hans": "插电式混合动力汽车在与电动汽车竞争对手的竞争中获得优势\n",
  "headline_zh-Hant": "插電式混合動力汽車在與電動汽車競爭對手的競爭中獲得優勢\n",
  "@context": [
    "https://schema.org",
    {
      "@vocab": "http://schema.org/",
      "@language": "en",
      "headline_zh-Hans": {
        "@id": "headline",
        "@language": "zh-Hans"
      },
      "headline_zh-Hant": {
        "@id": "headline",
        "@language": "zh-Hant"
      },
      "@version": 1.1,
      "description_zh-Hans": {
        "@id": "description",
        "@language": "zh-Hans"
      },
      "description_zh-Hant": {
        "@id": "description",
        "@language": "zh-Hant"
      }
    }
  ],
  "description_zh-Hans": "仅靠电力就能进行短途旅行的汽车销量激增，而在长途旅行中则有汽油发动机。\n",
  "description_zh-Hant": "僅靠電力就能進行短途旅行的汽車銷量激增，而在長途旅行中則有汽油發動機。\n"
}