{
  "@type": "NewsArticle",
  "identifier": "2022--07--14--en--myfeed--HackerNews--NewsArticle--32099509",
  "url": "https://news.ycombinator.com/item?id=32099509",
  "headline": "Scam apps still active on App Store – steal over $100M annually",
  "publisher": {
    "@type": "Organization",
    "name": "HackerNews",
    "url": "https://news.ycombinator.com",
    "logo": "https://hn.buzzing.cc/avatar.png"
  },
  "description": "",
  "keywords": [],
  "author": {
    "@type": "Person",
    "name": "keleftheriou",
    "url": "https://news.ycombinator.com/user?id=keleftheriou"
  },
  "discussionUrl": "https://news.ycombinator.com/item?id=32099509",
  "sameAs": "https://www.laptopmag.com/news/84-scam-apps-still-active-on-app-store-steal-over-dollar100-million-annually",
  "dateCreated": "2022-07-14T18:32:17.602Z",
  "datePublished": "2022-07-14T18:08:36.000Z",
  "dateModified": "2022-07-14T18:32:17.602Z",
  "interactionStatistic": [
    {
      "@type": "InteractionCounter",
      "interactionType": {
        "@type": "LikeAction"
      },
      "userInteractionCount": 3
    },
    {
      "@type": "InteractionCounter",
      "interactionType": {
        "@type": "CommentAction"
      },
      "userInteractionCount": 0
    }
  ],
  "headline_zh-Hans": "欺诈性应用程序仍然活跃在App Store上--每年盗取超过1亿美元的资金\n",
  "headline_zh-Hant": "欺詐性應用程序仍然活躍在App Store上--每年盜取超過1億美元的資金\n",
  "@context": [
    "https://schema.org",
    {
      "@vocab": "http://schema.org/",
      "@language": "en",
      "headline_zh-Hans": {
        "@id": "headline",
        "@language": "zh-Hans"
      },
      "headline_zh-Hant": {
        "@id": "headline",
        "@language": "zh-Hant"
      },
      "@version": 1.1
    }
  ]
}