{
  "@type": "NewsArticle",
  "identifier": "2022--07--21--en--myfeed--HackerNews--NewsArticle--32183302",
  "url": "https://news.ycombinator.com/item?id=32183302",
  "headline": "Potentials signs of fabrication threaten reigning theory of Alzheimer's disease",
  "publisher": {
    "@type": "Organization",
    "name": "HackerNews",
    "url": "https://news.ycombinator.com",
    "logo": "https://hn.buzzing.cc/avatar.png"
  },
  "description": "",
  "keywords": [],
  "author": {
    "@type": "Person",
    "name": "panabee",
    "url": "https://news.ycombinator.com/user?id=panabee"
  },
  "discussionUrl": "https://news.ycombinator.com/item?id=32183302",
  "sameAs": "https://www.science.org/content/article/potential-fabrication-research-images-threatens-key-theory-alzheimers-disease",
  "dateCreated": "2022-07-21T19:26:01.117Z",
  "datePublished": "2022-07-21T18:54:37.000Z",
  "dateModified": "2022-07-21T19:26:01.117Z",
  "interactionStatistic": [
    {
      "@type": "InteractionCounter",
      "interactionType": {
        "@type": "LikeAction"
      },
      "userInteractionCount": 13
    },
    {
      "@type": "InteractionCounter",
      "interactionType": {
        "@type": "CommentAction"
      },
      "userInteractionCount": 0
    }
  ],
  "headline_zh-Hans": "编造的潜在迹象威胁到阿尔茨海默病的统治理论\n",
  "headline_zh-Hant": "編造的潛在跡象威脅到阿爾茨海默病的統治理論\n",
  "@context": [
    "https://schema.org",
    {
      "@vocab": "http://schema.org/",
      "@language": "en",
      "headline_zh-Hans": {
        "@id": "headline",
        "@language": "zh-Hans"
      },
      "headline_zh-Hant": {
        "@id": "headline",
        "@language": "zh-Hant"
      },
      "@version": 1.1
    }
  ]
}