{
  "@type": "NewsArticle",
  "identifier": "2022--06--28--en--myfeed--HackerNews--NewsArticle--31907250",
  "url": "https://news.ycombinator.com/item?id=31907250",
  "headline": "Demystifying pack and unpack, these most misunderstood functions",
  "publisher": {
    "@type": "Organization",
    "name": "HackerNews",
    "url": "https://news.ycombinator.com",
    "logo": "https://hn.buzzing.cc/avatar.png"
  },
  "description": "",
  "keywords": [],
  "author": {
    "@type": "Person",
    "name": "psychoslave",
    "url": "https://news.ycombinator.com/user?id=psychoslave"
  },
  "discussionUrl": "https://news.ycombinator.com/item?id=31907250",
  "sameAs": "https://perldoc.perl.org/perlpacktut",
  "dateCreated": "2022-06-28T13:46:30.161Z",
  "datePublished": "2022-06-28T13:14:31.000Z",
  "dateModified": "2022-06-28T13:46:30.161Z",
  "interactionStatistic": [
    {
      "@type": "InteractionCounter",
      "interactionType": {
        "@type": "LikeAction"
      },
      "userInteractionCount": 2
    },
    {
      "@type": "InteractionCounter",
      "interactionType": {
        "@type": "CommentAction"
      },
      "userInteractionCount": 0
    }
  ],
  "headline_zh-Hans": "解读打包和拆包，这些最被误解的功能\n",
  "headline_zh-Hant": "解讀打包和拆包，這些最被誤解的功能\n",
  "@context": [
    "https://schema.org",
    {
      "@vocab": "http://schema.org/",
      "@language": "en",
      "headline_zh-Hans": {
        "@id": "headline",
        "@language": "zh-Hans"
      },
      "headline_zh-Hant": {
        "@id": "headline",
        "@language": "zh-Hant"
      },
      "@version": 1.1
    }
  ]
}