{
  "@type": "NewsArticle",
  "identifier": "2022--06--21--en--myfeed--HackerNews--NewsArticle--31818976",
  "url": "https://news.ycombinator.com/item?id=31818976",
  "headline": "Seattle Offers Utility Pole EV Chargers to City Residents",
  "publisher": {
    "@type": "Organization",
    "name": "HackerNews",
    "url": "https://news.ycombinator.com",
    "logo": "https://hn.buzzing.cc/avatar.png"
  },
  "description": "",
  "keywords": [],
  "author": {
    "@type": "Person",
    "name": "toomuchtodo",
    "url": "https://news.ycombinator.com/user?id=toomuchtodo"
  },
  "discussionUrl": "https://news.ycombinator.com/item?id=31818976",
  "sameAs": "https://cleantechnica.com/2022/06/20/seattle-offers-utility-pole-ev-chargers-to-city-residents/",
  "dateCreated": "2022-06-21T04:23:15.417Z",
  "datePublished": "2022-06-21T02:10:18.000Z",
  "dateModified": "2022-06-21T04:23:15.417Z",
  "interactionStatistic": [
    {
      "@type": "InteractionCounter",
      "interactionType": {
        "@type": "LikeAction"
      },
      "userInteractionCount": 2
    },
    {
      "@type": "InteractionCounter",
      "interactionType": {
        "@type": "CommentAction"
      },
      "userInteractionCount": 0
    }
  ],
  "headline_zh-Hans": "西雅图向城市居民提供电线杆电动车充电器\n",
  "headline_zh-Hant": "西雅圖向城市居民提供電線杆電動車充電器\n",
  "@context": [
    "https://schema.org",
    {
      "@vocab": "http://schema.org/",
      "@language": "en",
      "headline_zh-Hans": {
        "@id": "headline",
        "@language": "zh-Hans"
      },
      "headline_zh-Hant": {
        "@id": "headline",
        "@language": "zh-Hant"
      },
      "@version": 1.1
    }
  ]
}