{
  "@type": "NewsArticle",
  "identifier": "2022--08--22--en--myfeed--HackerNews--NewsArticle--32554108",
  "url": "https://news.ycombinator.com/item?id=32554108",
  "headline": "UK inflation to top% in early 2023, Citi warns",
  "publisher": {
    "@type": "Organization",
    "name": "HackerNews",
    "url": "https://news.ycombinator.com",
    "logo": "https://hn.buzzing.cc/avatar.png"
  },
  "description": "",
  "keywords": [],
  "author": {
    "@type": "Person",
    "name": "davidbarker",
    "url": "https://news.ycombinator.com/user?id=davidbarker"
  },
  "discussionUrl": "https://news.ycombinator.com/item?id=32554108",
  "sameAs": "https://www.reuters.com/world/uk/uk-inflation-hit-18-early-2023-citi-forecasts-2022-08-22/",
  "dateCreated": "2022-08-22T17:37:34.769Z",
  "datePublished": "2022-08-22T16:58:34.000Z",
  "dateModified": "2022-08-22T17:37:34.769Z",
  "interactionStatistic": [
    {
      "@type": "InteractionCounter",
      "interactionType": {
        "@type": "LikeAction"
      },
      "userInteractionCount": 2
    },
    {
      "@type": "InteractionCounter",
      "interactionType": {
        "@type": "CommentAction"
      },
      "userInteractionCount": 1
    }
  ],
  "headline_zh-Hans": "花旗银行警告说，英国通胀率将在2023年初达到顶峰\n",
  "headline_zh-Hant": "花旗銀行警告說，英國通脹率將在2023年初達到頂峰\n",
  "@context": [
    "https://schema.org",
    {
      "@vocab": "http://schema.org/",
      "@language": "en",
      "headline_zh-Hans": {
        "@id": "headline",
        "@language": "zh-Hans"
      },
      "headline_zh-Hant": {
        "@id": "headline",
        "@language": "zh-Hant"
      },
      "@version": 1.1
    }
  ]
}