{
  "@type": "NewsArticle",
  "identifier": "2022--08--19--en--myfeed--rss--NewsArticle--a208a229bf25c949f799de82bf929991",
  "url": "http://cacm.acm.org/magazines/2022/9/263790-technology-and-democracy",
  "headline": "Technology and Democracy",
  "publisher": {
    "@type": "Organization",
    "name": "cacm.acm.org",
    "url": "https://cacm.acm.org/magazine.rss"
  },
  "description": "&lt;p&gt;Computing has become highly important in everyday life during the past 75 years. In addition to its many benefits, however, it has also played a major role in driving societal polarization.&lt;/p&gt;",
  "keywords": [],
  "author": {
    "@type": "Person",
    "name": "unknown",
    "url": "https://cacm.acm.org/magazine.rss"
  },
  "discussionUrl": "http://cacm.acm.org/magazines/2022/9/263790-technology-and-democracy",
  "sameAs": "http://cacm.acm.org/magazines/2022/9/263790-technology-and-democracy",
  "dateCreated": "2022-08-19T18:35:36.167Z",
  "datePublished": "2022-09-01T04:00:00.000Z",
  "dateModified": "2022-08-19T18:35:36.167Z",
  "interactionStatistic": [],
  "headline_zh-Hans": "技术与民主\n",
  "headline_zh-Hant": "技術與民主\n",
  "@context": [
    "https://schema.org",
    {
      "@vocab": "http://schema.org/",
      "@language": "en",
      "headline_zh-Hans": {
        "@id": "headline",
        "@language": "zh-Hans"
      },
      "headline_zh-Hant": {
        "@id": "headline",
        "@language": "zh-Hant"
      },
      "@version": 1.1,
      "description_zh-Hans": {
        "@id": "description",
        "@language": "zh-Hans"
      },
      "description_zh-Hant": {
        "@id": "description",
        "@language": "zh-Hant"
      }
    }
  ],
  "description_zh-Hans": "&lt;p&gt;在过去的75年中，计算在日常生活中变得非常重要。然而，除了它的许多好处之外，它也在推动社会两极分化方面发挥了重要作用&lt;/p&gt。\n",
  "description_zh-Hant": "&lt;p&gt;在過去的75年中，計算在日常生活中變得非常重要。然而，除了它的許多好處之外，它也在推動社會兩極分化方面發揮了重要作用&lt;/p&gt。\n"
}