{
  "@type": "NewsArticle",
  "identifier": "2022--07--15--en--askhn--HackerNews--NewsArticle--32108993",
  "url": "https://news.ycombinator.com/item?id=32108993",
  "headline": "Ask HN: Recommend a tokenization solution for AWS RDS to protect sensitive data?",
  "publisher": {
    "@type": "Organization",
    "name": "HackerNews",
    "url": "https://news.ycombinator.com",
    "logo": "https://hn.buzzing.cc/avatar.png"
  },
  "description": "I have to tokenize the sensitive data stored in AWS. Does AWS have an tokenization service? If possible, I want to avoid third party services outside of AWS.",
  "keywords": [
    "Ask HN"
  ],
  "genre": "Ask HN",
  "author": {
    "@type": "Person",
    "name": "dev_0",
    "url": "https://news.ycombinator.com/user?id=dev_0"
  },
  "discussionUrl": "https://news.ycombinator.com/item?id=32108993",
  "sameAs": "https://news.ycombinator.com/item?id=32108993",
  "dateCreated": "2022-07-15T15:31:47.440Z",
  "datePublished": "2022-07-15T15:14:00.000Z",
  "dateModified": "2022-07-15T15:31:47.440Z",
  "interactionStatistic": [
    {
      "@type": "InteractionCounter",
      "interactionType": {
        "@type": "LikeAction"
      },
      "userInteractionCount": 1
    },
    {
      "@type": "InteractionCounter",
      "interactionType": {
        "@type": "CommentAction"
      },
      "userInteractionCount": 0
    }
  ],
  "headline_zh-Hans": "Ask HN: 为AWS RDS推荐一个标记化解决方案，以保护敏感数据？\n",
  "headline_zh-Hant": "Ask HN: 為AWS RDS推薦一個標記化解決方案，以保護敏感數據？\n",
  "@context": [
    "https://schema.org",
    {
      "@vocab": "http://schema.org/",
      "@language": "en",
      "headline_zh-Hans": {
        "@id": "headline",
        "@language": "zh-Hans"
      },
      "headline_zh-Hant": {
        "@id": "headline",
        "@language": "zh-Hant"
      },
      "@version": 1.1,
      "description_zh-Hans": {
        "@id": "description",
        "@language": "zh-Hans"
      },
      "description_zh-Hant": {
        "@id": "description",
        "@language": "zh-Hant"
      }
    }
  ],
  "description_zh-Hans": "我必须对存储在AWS中的敏感数据进行标记化。AWS是否有代币化服务？如果可能的话，我想避免使用AWS之外的第三方服务。\n",
  "description_zh-Hant": "我必須對存儲在AWS中的敏感數據進行標記化。AWS是否有代幣化服務？如果可能的話，我想避免使用AWS之外的第三方服務。\n"
}